proxy_inspector.py
useragents.py
proxy_inspector-0.0.5.dist-info/METADATA
proxy_inspector-0.0.5.dist-info/WHEEL
proxy_inspector-0.0.5.dist-info/namespace_packages.txt
proxy_inspector-0.0.5.dist-info/top_level.txt
proxy_inspector-0.0.5.dist-info/zip-safe
proxy_inspector-0.0.5.dist-info/RECORD
